LICENSE
MANIFEST.in
README.rst
gen_openSUSE_dedups
gen_packman_dedups
install_symlinked_scripts.py
setup.py
squid_dedup.py
conf/opensuse.conf
conf/packman.conf
squid_dedup/__init__.py
squid_dedup/config.py
squid_dedup/dedup.py
squid_dedup/fetch.py
squid_dedup/main.py
squid_dedup.egg-info/PKG-INFO
squid_dedup.egg-info/SOURCES.txt
squid_dedup.egg-info/dependency_links.txt
squid_dedup.egg-info/entry_points.txt
squid_dedup.egg-info/top_level.txt
squid_dedup/lib/__init__.py
squid_dedup/lib/configfile.py
squid_dedup/lib/frec.py
squid_dedup/lib/logsetup.py
squid_dedup/lib/profile.py
squid_dedup/lib/record.py
squid_dedup/lib/skel.py
squid_dedup/test/test_configfile.py
squid_dedup/test/test_frec.py
squid_dedup/test/test_record.py
squid_dedup/utils/gen_openSUSE_dedups.py
squid_dedup/utils/gen_openSUSE_redirects.py
squid_dedup/utils/gen_packman_dedups.py
squid_dedup/utils/update-date.py